cthreepo/__init__.py
cthreepo/converters.py
cthreepo/fetch_assm_report.py
cthreepo/mapfiles/h37.map
cthreepo/mapfiles/h38.map
cthreepo/mapfiles/m37.map
cthreepo/mapfiles/m38.map
cthreepo-0.1.3.dist-info/METADATA
cthreepo-0.1.3.dist-info/WHEEL
cthreepo-0.1.3.dist-info/entry_points.txt
cthreepo-0.1.3.dist-info/top_level.txt
cthreepo-0.1.3.dist-info/RECORD
