Metadata-Version: 2.1
Name: cthreepo
Version: 0.1.3
Summary: A python tool to interconvert seq-ids in gff3, gtf, bed and other files.
Home-page: http://github.com/vkkodali/cthreepo
Author: Vamsi Kodali
Author-email: vkkodali@gmail.com
License: MIT
Requires-Dist: requests
